LICENSE
MANIFEST.in
NOTICE
README.rst
THANKS
UNLICENSE
setup.py
examples/test_eventlet.py
examples/test_gevent.py
examples/test_threaded.py
socketpool/__init__.py
socketpool/backend_eventlet.py
socketpool/backend_gevent.py
socketpool/backend_thread.py
socketpool/conn.py
socketpool/pool.py
socketpool/util.py
socketpool.egg-info/PKG-INFO
socketpool.egg-info/SOURCES.txt
socketpool.egg-info/dependency_links.txt
socketpool.egg-info/top_level.txt